UKCaseLawScraper/CaseHeaderScraper.py
UKCaseLawScraper/CaseInfoScraper.py
UKCaseLawScraper/FullTextScraper.py
UKCaseLawScraper/Save_to_json.py
UKCaseLawScraper/__init__.py
tests/__init__.py
tests/test_module1.py
tests/test_module2.py
tests/test_module3.py
UKCaseLawScraper-0.1.dist-info/LICENSE
UKCaseLawScraper-0.1.dist-info/METADATA
UKCaseLawScraper-0.1.dist-info/WHEEL
UKCaseLawScraper-0.1.dist-info/top_level.txt
UKCaseLawScraper-0.1.dist-info/RECORD
