Metadata-Version: 2.1
Name: UKCaseLawScraper
Version: 0.1
Summary: A package for scrape case law informations.
Home-page: https://github.com/mrjoneidi/UKCaseLawScraper
Author: Mohammadreza Joneidi Jafari
Author-email: m.r.joneidi.02@gmail.com
Classifier: Programming Language :: Python :: 3
Classifier: License :: OSI Approved :: MIT License
Classifier: Operating System :: OS Independent
Requires-Python: >=3.6
License-File: LICENSE
